MANIFEST.in
README.rst
setup.py
LemonFramework.egg-info/PKG-INFO
LemonFramework.egg-info/SOURCES.txt
LemonFramework.egg-info/dependency_links.txt
LemonFramework.egg-info/requires.txt
LemonFramework.egg-info/top_level.txt
lemon/__init__.py
lemon/aspects/__init__.py
lemon/aspects/logging.py
lemon/aspects/session.py
lemon/aspects/debug/__init__.py
lemon/aspects/debug/config.py
lemon/aspects/flow/__init__.py
lemon/aspects/flow/servingfiles.py
lemon/config/__init__.py
lemon/config/configbase.py
lemon/controllers/__init__.py
lemon/controllers/controllerbase.py
lemon/controllers/simple.py
lemon/core/__init__.py
lemon/core/exceptions.py
lemon/core/aspects/__init__.py
lemon/core/aspects/aspectbase.py
lemon/core/aspects/aspecttype.py
lemon/core/config/__init__.py
lemon/core/config/configtype.py
lemon/core/config/exceptions.py
lemon/core/config/utils.py
lemon/core/config/urls/__init__.py
lemon/core/config/urls/resource.py
lemon/core/handlers/__init__.py
lemon/core/handlers/handlerbase.py
lemon/core/handlers/wsgi.py
lemon/core/sessions/__init__.py
lemon/core/sessions/exceptions.py
lemon/core/sessions/filesystem.py
lemon/core/sessions/sessionbase.py
lemon/core/template/config.py
lemon/core/template/manage.py
lemon/core/template/apps/__init__.py
lemon/core/utils/__init__.py
lemon/core/utils/imports.py
lemon/core/utils/decorators/__init__.py
lemon/core/utils/patterns/__init__.py
lemon/core/utils/patterns/singleton.py
lemon/http/__init__.py
lemon/http/client_error.py
lemon/http/exceptions.py
lemon/http/informational.py
lemon/http/redirection.py
lemon/http/request.py
lemon/http/response.py
lemon/http/server_error.py
lemon/http/successful.py
lemon/http/parser/__init__.py
lemon/http/parser/expressions.py
lemon/renders/__init__.py
lemon/renders/base.py
lemon/renders/exceptions.py
lemon/renders/json.py
lemon/renders/templates.py
tests/__init__.py