Metadata-Version: 1.1
Name: LemonFramework
Version: 0.0.1
Summary: Agile Web Framework.
Home-page: https://github.com/LemonFramework/LemonFramework
Author: Vicente Ruiz Rodríguez
Author-email: vruiz2.0@gmail.com
License: GPLv3
Keywords: agile web framework
Platform: UNKNOWN
Classifier: Development Status :: 1 - Planning
Classifier: Development Status :: 2 - Pre-Alpha
Classifier: Environment :: Web Environment
Classifier: License :: OSI Approved :: GNU General Public License v3 (GPLv3)
Classifier: Programming Language :: Python :: 3
Classifier: Topic :: Database
Classifier: Topic :: Internet :: WWW/HTTP
Classifier: Topic :: Internet :: WWW/HTTP :: Dynamic Content
Classifier: Topic :: Internet :: WWW/HTTP :: Session
Classifier: Topic :: Internet :: WWW/HTTP :: WSGI
Classifier: Topic :: Software Development :: Libraries :: Application Frameworks
